Metadata-Version: 2.4
Name: nvidia-crfm-helm
Version: 25.9.1
Summary: NVIDIA: Benchmark for language models - Fork of Stanford CRFM HELM
Home-page: https://github.com/stanford-crfm/helm
Author: Stanford CRFM, NVIDIA
Author-email: contact-crfm@stanford.edu
License: Apache License 2.0
Project-URL: Original Project, https://github.com/stanford-crfm/helm
Project-URL: Original Documentation, https://crfm.stanford.edu/helm
Keywords: language models benchmarking nvidia fork stanford crfm helm
Classifier: Programming Language :: Python :: 3
Classifier: Programming Language :: Python :: 3 :: Only
Classifier: Programming Language :: Python :: 3.9
Classifier: Programming Language :: Python :: 3.10
Classifier: Programming Language :: Python :: 3.11
Classifier: License :: OSI Approved :: Apache Software License
Requires-Python: >=3.9
License-File: LICENSE
Requires-Dist: cattrs~=22.2
Requires-Dist: colorlog~=6.9
Requires-Dist: dacite~=1.6
Requires-Dist: importlib-resources~=5.10
Requires-Dist: Mako~=1.2
Requires-Dist: numpy<3,~=1.26
Requires-Dist: pandas~=2.0
Requires-Dist: pyhocon~=0.3.59
Requires-Dist: retrying~=1.3
Requires-Dist: spacy~=3.5
Requires-Dist: srsly>=2.4.8
Requires-Dist: preshed>=3.0.8
Requires-Dist: spacy-legacy>=3.0.11
Requires-Dist: spacy-loggers>=1.0.4
Requires-Dist: murmurhash>=1.0.8
Requires-Dist: tqdm~=4.64
Requires-Dist: zstandard~=0.18.0
Requires-Dist: diskcache>=5.0.0
Requires-Dist: bottle~=0.12.23
Requires-Dist: datasets~=2.17
Requires-Dist: pyarrow>=11.0.0
Requires-Dist: pyarrow-hotfix~=0.6
Requires-Dist: nltk!=3.9.0,~=3.7
Requires-Dist: rouge-score~=0.1.2
Requires-Dist: scipy~=1.10
Requires-Dist: uncertainty-calibration~=0.1.4
Requires-Dist: scikit-learn~=1.1
Requires-Dist: transformers~=4.40
Requires-Dist: torch<3.0.0,>=1.13.1
Requires-Dist: torchvision<3.0.0,>=0.14.1
Requires-Dist: python-docx==1.2.0
Requires-Dist: nemo-evaluator
Provides-Extra: proxy-server
Requires-Dist: gunicorn>=20.1; extra == "proxy-server"
Provides-Extra: human-evaluation
Requires-Dist: scaleapi~=2.13.0; extra == "human-evaluation"
Requires-Dist: surge-api~=1.1.0; extra == "human-evaluation"
Provides-Extra: scenarios
Requires-Dist: gdown~=5.1; extra == "scenarios"
Requires-Dist: sympy~=1.11.1; extra == "scenarios"
Requires-Dist: xlrd~=2.0.1; extra == "scenarios"
Provides-Extra: metrics
Requires-Dist: google-api-python-client~=2.64; extra == "metrics"
Requires-Dist: numba~=0.56; extra == "metrics"
Requires-Dist: sacrebleu~=2.2.1; extra == "metrics"
Requires-Dist: langdetect~=1.0.9; extra == "metrics"
Requires-Dist: immutabledict~=4.2.0; extra == "metrics"
Requires-Dist: gradio_client~=1.3; extra == "metrics"
Provides-Extra: ranking
Requires-Dist: pytrec_eval==0.5; extra == "ranking"
Provides-Extra: summarization
Requires-Dist: bert-score~=0.3; extra == "summarization"
Provides-Extra: plots
Requires-Dist: colorcet~=3.0.1; extra == "plots"
Requires-Dist: matplotlib~=3.6.0; extra == "plots"
Requires-Dist: seaborn~=0.11.0; extra == "plots"
Provides-Extra: decodingtrust
Requires-Dist: fairlearn~=0.9.0; extra == "decodingtrust"
Provides-Extra: slurm
Requires-Dist: simple-slurm~=0.2.6; extra == "slurm"
Provides-Extra: cleva
Requires-Dist: unidecode~=1.3; extra == "cleva"
Requires-Dist: pypinyin~=0.49.0; extra == "cleva"
Requires-Dist: jieba~=0.42.1; extra == "cleva"
Requires-Dist: opencc~=1.1; extra == "cleva"
Requires-Dist: langdetect~=1.0; extra == "cleva"
Provides-Extra: images
Requires-Dist: pillow~=10.2; extra == "images"
Provides-Extra: mongo
Requires-Dist: pymongo~=4.2; extra == "mongo"
Provides-Extra: unitxt
Requires-Dist: evaluate~=0.4.1; extra == "unitxt"
Provides-Extra: seahelm
Requires-Dist: pythainlp==5.0.0; extra == "seahelm"
Requires-Dist: pyonmttok==1.37.0; extra == "seahelm"
Requires-Dist: sacrebleu~=2.2.1; extra == "seahelm"
Requires-Dist: python-crfsuite~=0.9.11; extra == "seahelm"
Provides-Extra: accelerate
Requires-Dist: accelerate~=0.25; extra == "accelerate"
Provides-Extra: aleph-alpha
Requires-Dist: aleph-alpha-client~=2.14.0; extra == "aleph-alpha"
Requires-Dist: tokenizers>=0.13.3; extra == "aleph-alpha"
Provides-Extra: allenai
Requires-Dist: ai2-olmo~=0.2; extra == "allenai"
Provides-Extra: amazon
Requires-Dist: boto3~=1.34.131; extra == "amazon"
Requires-Dist: awscli~=1.33.13; extra == "amazon"
Requires-Dist: botocore~=1.34.131; extra == "amazon"
Provides-Extra: anthropic
Requires-Dist: anthropic~=0.48; extra == "anthropic"
Requires-Dist: websocket-client~=1.3.2; extra == "anthropic"
Requires-Dist: httpx<0.28.0; extra == "anthropic"
Provides-Extra: cohere
Requires-Dist: cohere~=5.3; extra == "cohere"
Provides-Extra: writer
Requires-Dist: writerai~=4.0; extra == "writer"
Provides-Extra: mistral
Requires-Dist: mistralai~=1.1; extra == "mistral"
Provides-Extra: openai
Requires-Dist: openai~=1.70; extra == "openai"
Requires-Dist: tiktoken~=0.7; extra == "openai"
Requires-Dist: pydantic~=2.0; extra == "openai"
Provides-Extra: google
Requires-Dist: google-cloud-aiplatform~=1.48; extra == "google"
Provides-Extra: together
Requires-Dist: together~=1.1; extra == "together"
Provides-Extra: yandex
Requires-Dist: sentencepiece~=0.2.0; extra == "yandex"
Provides-Extra: reka
Requires-Dist: reka-api~=2.0.0; extra == "reka"
Provides-Extra: vlm
Requires-Dist: einops~=0.7.0; extra == "vlm"
Requires-Dist: einops-exts~=0.0.4; extra == "vlm"
Requires-Dist: open-clip-torch~=2.24; extra == "vlm"
Requires-Dist: torch~=2.1; extra == "vlm"
Requires-Dist: transformers_stream_generator~=0.0.4; extra == "vlm"
Requires-Dist: scipy~=1.10; extra == "vlm"
Requires-Dist: torchvision<3.0.0,>=0.14.1; extra == "vlm"
Provides-Extra: medhelm
Requires-Dist: aiohttp<4.0.0,>=3.12.13; extra == "medhelm"
Requires-Dist: anthropic<1.0.0,>=0.57.1; extra == "medhelm"
Requires-Dist: bert-score<1.0.0,>=0.3.13; extra == "medhelm"
Requires-Dist: bottle<1.0.0,>=0.12.25; extra == "medhelm"
Requires-Dist: datasets<3.0.0,>=2.21.0; extra == "medhelm"
Requires-Dist: Flask<4.0.0,>=3.0.3; extra == "medhelm"
Requires-Dist: gin-config<1.0.0,>=0.5.0; extra == "medhelm"
Requires-Dist: huggingface-hub<1.0.0,>=0.33.1; extra == "medhelm"
Requires-Dist: lxml<7.0.0,>=6.0.0; extra == "medhelm"
Requires-Dist: matplotlib<4.0.0,>=3.10.3; extra == "medhelm"
Requires-Dist: nltk<4.0.0,>=3.9.1; extra == "medhelm"
Requires-Dist: numpy<2.0.0,>=1.26.4; extra == "medhelm"
Requires-Dist: openai<2.0.0,>=1.93.0; extra == "medhelm"
Requires-Dist: openpyxl<4.0.0,>=3.1.5; extra == "medhelm"
Requires-Dist: pandas<3.0.0,>=2.3.0; extra == "medhelm"
Requires-Dist: parameterized<1.0.0,>=0.9.0; extra == "medhelm"
Requires-Dist: pillow<12.0.0,>=11.3.0; extra == "medhelm"
Requires-Dist: protobuf<7.0.0,>=6.31.1; extra == "medhelm"
Requires-Dist: psutil<7.0.0,>=6.0.0; extra == "medhelm"
Requires-Dist: pyarrow<21.0.0,>=20.0.0; extra == "medhelm"
Requires-Dist: pyarrow-hotfix<1.0.0,>=0.7; extra == "medhelm"
Requires-Dist: pydantic<3.0.0,>=2.11.7; extra == "medhelm"
Requires-Dist: python-dateutil<3.0.0,>=2.9.0.post0; extra == "medhelm"
Requires-Dist: python-docx<2.0.0,>=1.2.0; extra == "medhelm"
Requires-Dist: python-dotenv<2.0.0,>=1.1.1; extra == "medhelm"
Requires-Dist: PyYAML<7.0.0,>=6.0.2; extra == "medhelm"
Requires-Dist: regex<2025.0.0,>=2024.11.6; extra == "medhelm"
Requires-Dist: requests<3.0.0,>=2.32.4; extra == "medhelm"
Requires-Dist: retrying<2.0.0,>=1.4.0; extra == "medhelm"
Requires-Dist: rich<15.0.0,>=14.0.0; extra == "medhelm"
Requires-Dist: rouge_score<1.0.0,>=0.1.2; extra == "medhelm"
Requires-Dist: scikit-learn<2.0.0,>=1.7.0; extra == "medhelm"
Requires-Dist: scipy<2.0.0,>=1.10.0; extra == "medhelm"
Requires-Dist: sentencepiece<1.0.0,>=0.2.0; extra == "medhelm"
Requires-Dist: setuptools<81.0.0,>=80.9.0; extra == "medhelm"
Requires-Dist: six<2.0.0,>=1.17.0; extra == "medhelm"
Requires-Dist: smart-open<8.0.0,>=7.1.0; extra == "medhelm"
Requires-Dist: spacy<4.0.0,>=3.8.7; extra == "medhelm"
Requires-Dist: structlog<25.0.0,>=24.1.0; extra == "medhelm"
Requires-Dist: sympy<2.0.0,>=1.14.0; extra == "medhelm"
Requires-Dist: tiktoken<1.0.0,>=0.9.0; extra == "medhelm"
Requires-Dist: tokenizers<1.0.0,>=0.21.2; extra == "medhelm"
Requires-Dist: toml<1.0.0,>=0.10.2; extra == "medhelm"
Requires-Dist: torch<3.0.0,>=2.7.1; extra == "medhelm"
Requires-Dist: torchvision<1.0.0,>=0.22.1; extra == "medhelm"
Requires-Dist: tqdm<5.0.0,>=4.67.1; extra == "medhelm"
Requires-Dist: transformers<5.0.0,>=4.53.0; extra == "medhelm"
Requires-Dist: triton<4.0.0,>=3.3.1; extra == "medhelm"
Requires-Dist: typer<1.0.0,>=0.16.0; extra == "medhelm"
Requires-Dist: typing_extensions<5.0.0,>=4.14.0; extra == "medhelm"
Requires-Dist: uncertainty-calibration<1.0.0,>=0.1.4; extra == "medhelm"
Requires-Dist: websocket-client<2.0.0,>=1.3.3; extra == "medhelm"
Requires-Dist: xmltodict<1.0.0,>=0.14.2; extra == "medhelm"
Requires-Dist: yq<4.0.0,>=3.1.1; extra == "medhelm"
Requires-Dist: zstandard<1.0.0,>=0.18.0; extra == "medhelm"
Dynamic: author
Dynamic: author-email
Dynamic: classifier
Dynamic: description
Dynamic: description-content-type
Dynamic: home-page
Dynamic: keywords
Dynamic: license
Dynamic: license-file
Dynamic: project-url
Dynamic: provides-extra
Dynamic: requires-dist
Dynamic: requires-python
Dynamic: summary
